i2csense/__init__.py
i2csense/__main__.py
i2csense/bh1750.py
i2csense/bme280.py
i2csense/htu21d.py
i2csense-0.0.4.dist-info/DESCRIPTION.rst
i2csense-0.0.4.dist-info/METADATA
i2csense-0.0.4.dist-info/RECORD
i2csense-0.0.4.dist-info/WHEEL
i2csense-0.0.4.dist-info/entry_points.txt
i2csense-0.0.4.dist-info/metadata.json
i2csense-0.0.4.dist-info/top_level.txt
