Metadata-Version: 2.0
Name: i2csense
Version: 0.0.4
Summary: A library to handle i2c sensors with the Raspberry Pi
Home-page: https://github.com/azogue/i2csense
Author: Eugenio Panadero
Author-email: eugenio.panadero@gmail.com
License: MIT
Keywords: raspberry i2c sensors python3 bme280 bh1750 htu21d
Platform: UNKNOWN
Classifier: Development Status :: 3 - Alpha
Classifier: Environment :: Console
Classifier: Intended Audience :: Developers
Classifier: Intended Audience :: Education
Classifier: Topic :: Home Automation
Classifier: License :: OSI Approved :: MIT License
Classifier: Programming Language :: Python :: 3.4
Classifier: Programming Language :: Python :: 3.5
Classifier: Programming Language :: Python :: 3.6
Classifier: Operating System :: Unix
Requires-Dist: smbus-cffi (==0.5.1)
